maker_chief.py
maker_chief-0.1.2.dist-info/entry_points.txt
maker_chief-0.1.2.dist-info/WHEEL
maker_chief-0.1.2.dist-info/METADATA
maker_chief-0.1.2.dist-info/RECORD
