Metadata-Version: 2.1
Name: maker-chief
Version: 0.1.2
Summary: tally makerdao governance votes
Home-page: https://github.com/banteg/maker-chief
License: MIT
Author: banteg
Author-email: banteeg@gmail.com
Requires-Python: >=3.7,<4.0
Classifier: License :: OSI Approved :: MIT License
Classifier: Programming Language :: Python :: 3
Classifier: Programming Language :: Python :: 3.7
Requires-Dist: appdirs (>=1.4,<2.0)
Requires-Dist: click (>=7.0,<8.0)
Requires-Dist: eth-abi (>=1.3,<2.0)
Requires-Dist: eth-utils (>=1.4,<2.0)
Requires-Dist: requests (>=2.21,<3.0)
Requires-Dist: web3 (>=4.9,<5.0)
